nauron/__init__.py
nauron/__version__.py
nauron/helpers.py
nauron/mq_consumer.py
nauron/mq_producer.py
nauron/nauron.py
nauron/worker.py
nauron-1.2.2.dist-info/LICENSE
nauron-1.2.2.dist-info/METADATA
nauron-1.2.2.dist-info/WHEEL
nauron-1.2.2.dist-info/top_level.txt
nauron-1.2.2.dist-info/RECORD
