Metadata-Version: 2.1
Name: nauron
Version: 1.2.2
Summary: A Python library for creating distributed and scalable web services.
Home-page: https://github.com/TartuNLP/nauron
Author: University of Tartu
Author-email: ping@tartunlp.ai
License: GPLv3
Platform: UNKNOWN
Classifier: Programming Language :: Python :: 3
Classifier: License :: OSI Approved :: GNU General Public License v3 (GPLv3)
Classifier: Operating System :: OS Independent
Classifier: Development Status :: 4 - Beta
Classifier: Framework :: Flask
Requires-Dist: pika (>=1.1.0)
Requires-Dist: flask (>=1.1.2)
Requires-Dist: flask-cors (>=3.0.9)
Requires-Dist: dataclasses (>=0.7) ; python_version < "3.7.0"
